virtualsmoke/__init__.py
virtualsmoke/meanpathcaler.gz
virtualsmoke/mfp_model.h5
virtualsmoke/smoke.py
virtualsmoke-0.0.7.dist-info/LICENSE
virtualsmoke-0.0.7.dist-info/METADATA
virtualsmoke-0.0.7.dist-info/WHEEL
virtualsmoke-0.0.7.dist-info/top_level.txt
virtualsmoke-0.0.7.dist-info/RECORD
