Metadata-Version: 2.1
Name: virtualsmoke
Version: 0.0.7
Summary: A package for predicting fires given environmental variables
Home-page: https://nkrtech.com
Download-URL: https://github.com/moinonin/virtualsmoke/archive/refs/heads/main.zip
Author: Nicolus Rotich
Author-email: nicholas.rotich@gmail.com
License: MIT
Project-URL: Bug Tracker, https://github.com/pypa/virtualsmoke/issues
Platform: any
Classifier: License :: OSI Approved :: MIT License
Requires-Python: >=3.9
License-File: LICENSE
Requires-Dist: setuptools (>=58.1.0)
Requires-Dist: wheel (>=0.36.2)
Requires-Dist: sklearn (>=0.0)
Requires-Dist: h5py (>=3.6.0)
Requires-Dist: fire
